hanzo_cli/__init__.py
hanzo_cli/__main__.py
hanzo_cli/cli.py
hanzo_cli/commands/__init__.py
hanzo_cli/commands/agent.py
hanzo_cli/commands/auth.py
hanzo_cli/commands/chat.py
hanzo_cli/commands/cluster.py
hanzo_cli/commands/config.py
hanzo_cli/commands/mcp.py
hanzo_cli/commands/miner.py
hanzo_cli/commands/network.py
hanzo_cli/commands/repl.py
hanzo_cli/commands/tools.py
hanzo_cli/interactive/__init__.py
hanzo_cli/interactive/dashboard.py
hanzo_cli/interactive/repl.py
hanzo_cli/utils/__init__.py
hanzo_cli/utils/config.py
hanzo_cli/utils/output.py
hanzo_cli-0.1.0.dist-info/METADATA
hanzo_cli-0.1.0.dist-info/WHEEL
hanzo_cli-0.1.0.dist-info/entry_points.txt
hanzo_cli-0.1.0.dist-info/RECORD
