Metadata-Version: 2.4
Name: hanzo-cli
Version: 0.1.0
Summary: Unified CLI for Hanzo AI - Local, Private, Free AI Infrastructure
Project-URL: Homepage, https://hanzo.ai
Project-URL: Repository, https://github.com/hanzoai/python-sdk
Project-URL: Documentation, https://docs.hanzo.ai/cli
Project-URL: Changelog, https://github.com/hanzoai/python-sdk/blob/main/pkg/hanzo-cli/CHANGELOG.md
Project-URL: Bug Tracker, https://github.com/hanzoai/python-sdk/issues
Author-email: Hanzo AI <dev@hanzo.ai>
Keywords: agents,ai,cli,hanzo,llm,local-ai,mcp,private-ai
Classifier: Development Status :: 4 - Beta
Classifier: Environment :: Console
Classifier: Intended Audience :: Developers
Classifier: License :: OSI Approved :: Apache Software License
Classifier: Operating System :: OS Independent
Classifier: Programming Language :: Python :: 3
Classifier: Programming Language :: Python :: 3.8
Classifier: Programming Language :: Python :: 3.9
Classifier: Programming Language :: Python :: 3.10
Classifier: Programming Language :: Python :: 3.11
Classifier: Programming Language :: Python :: 3.12
Classifier: Topic :: Scientific/Engineering :: Artificial Intelligence
Classifier: Topic :: Software Development :: Libraries :: Python Modules
Requires-Python: >=3.8
Requires-Dist: click>=8.1.0
Requires-Dist: httpx>=0.23.0
Requires-Dist: prompt-toolkit>=3.0.0
Requires-Dist: pydantic>=2.0.0
Requires-Dist: pyyaml>=6.0
Requires-Dist: rich>=13.0.0
Requires-Dist: typer>=0.9.0
Provides-Extra: all
Requires-Dist: hanzo-a2a>=0.1.0; extra == 'all'
Requires-Dist: hanzo-agents>=0.1.0; extra == 'all'
Requires-Dist: hanzo-cluster>=0.1.0; extra == 'all'
Requires-Dist: hanzo-mcp>=0.1.0; extra == 'all'
Requires-Dist: hanzo-miner>=0.1.0; extra == 'all'
Requires-Dist: hanzo-network>=0.1.0; extra == 'all'
Requires-Dist: hanzo-repl>=0.1.0; extra == 'all'
Requires-Dist: hanzoai>=1.0.0; extra == 'all'
Provides-Extra: dev
Requires-Dist: black>=23.0.0; extra == 'dev'
Requires-Dist: mypy>=1.0.0; extra == 'dev'
Requires-Dist: pytest-asyncio>=0.21.0; extra == 'dev'
Requires-Dist: pytest-cov>=4.0.0; extra == 'dev'
Requires-Dist: pytest>=7.0.0; extra == 'dev'
Requires-Dist: ruff>=0.1.0; extra == 'dev'
Provides-Extra: repl
Requires-Dist: hanzo-repl>=0.1.0; extra == 'repl'
